<?xml version="1.0" encoding="utf-8"?>
<SoundBanksInfo Platform="Mac" BasePlatform="Mac" SchemaVersion="16" SoundBankVersion="145">
	<RootPaths>
		<ProjectRoot>../..</ProjectRoot>
		<SourceFilesRoot>../../.cache/Mac</SourceFilesRoot>
		<SoundBanksRoot>.</SoundBanksRoot>
		<ExternalSourcesInputFile></ExternalSourcesInputFile>
		<ExternalSourcesOutputRoot>.</ExternalSourcesOutputRoot>
	</RootPaths>
	<DialogueEvents/>
	<SoundBanks>
		<SoundBank Id="1328360421" Type="User" Language="SFX" Hash="{4EB64CBD-5EFF-E5D4-44AA-6E15EF3F8B2B}">
			<ShortName>MainSB</ShortName>
			<Path>MainSB.bnk</Path>
			<Plugins>
				<Custom>
					<Plugin Id="517724009" Name="Tone Generator" LibName="Wwise Tone Generator" LibId="6684674"/>
					<Plugin Id="537737653" Name="Tone Generator" LibName="Wwise Tone Generator" LibId="6684674"/>
				</Custom>
			</Plugins>
			<Events>
				<Event Id="4198308420" Name="enemies_movment" MaxAttenuation="0" DurationType="OneShot" DurationMin="0" DurationMax="0"/>
				<Event Id="162136643" Name="player_rollingMov_start" DurationType="Infinite">
					<PluginRefs>
						<Custom>
							<PluginRef Id="517724009"/>
							<PluginRef Id="537737653"/>
						</Custom>
					</PluginRefs>
				</Event>
				<Event Id="3305766081" Name="player_rollingMov_stop" MaxAttenuation="0" DurationType="OneShot" DurationMin="0" DurationMax="0"/>
			</Events>
			<GameParameters>
				<GameParameter Id="1833811084" Name="Player_velocity"/>
			</GameParameters>
		</SoundBank>
		<SoundBank Id="1355168291" Type="User" Language="SFX" Hash="{E47C0B91-6822-71F2-6158-F50BC5CD2F5A}">
			<ShortName>Init</ShortName>
			<Path>Init.bnk</Path>
			<Plugins>
				<AudioDevices>
					<Plugin Id="2317455096" Name="No_Output" LibName="No Output" LibId="11862023"/>
					<Plugin Id="3859886410" Name="System" LibName="System" LibId="11403271"/>
				</AudioDevices>
			</Plugins>
			<Busses>
				<Bus Id="3803692087" Name="Master Audio Bus"/>
			</Busses>
			<GameParameters>
				<GameParameter Id="1833811084" Name="Player_velocity"/>
			</GameParameters>
		</SoundBank>
	</SoundBanks>
	<FileHash>{A05F64A9-0D30-F22E-302C-C02E1F3F1FF1}</FileHash>
</SoundBanksInfo>
